[
  {
    "name": "第1关",
    "pathType": "quadratic",
    "curves": [
      {
        "p1": {
          "x": 480,
          "y": 270
        },
        "cp": {
          "x": 271,
          "y": 272
        },
        "p2": {
          "x": 146,
          "y": 272
        }
      },
      {
        "p1": {
          "x": 146,
          "y": 272
        },
        "cp": {
          "x": 76,
          "y": 272
        },
        "p2": {
          "x": 76,
          "y": 342
        }
      },
      {
        "p1": {
          "x": 76,
          "y": 342
        },
        "cp": {
          "x": 76,
          "y": 442
        },
        "p2": {
          "x": 76,
          "y": 542
        }
      },
      {
        "p1": {
          "x": 76,
          "y": 542
        },
        "cp": {
          "x": 76,
          "y": 612
        },
        "p2": {
          "x": 146,
          "y": 612
        }
      },
      {
        "p1": {
          "x": 146,
          "y": 612
        },
        "cp": {
          "x": 271,
          "y": 612
        },
        "p2": {
          "x": 396,
          "y": 612
        }
      }
    ],
    "waypoints": [
      {
        "x": 395,
        "y": 296
      },
      {
        "x": 119,
        "y": 299
      },
      {
        "x": 83,
        "y": 328
      },
      {
        "x": 75,
        "y": 374
      },
      {
        "x": 76,
        "y": 578
      },
      {
        "x": 95,
        "y": 621
      },
      {
        "x": 140,
        "y": 636
      },
      {
        "x": 395,
        "y": 636
      }
    ],
    "shooterPos": {
      "x": 216,
      "y": 442
    },
    "background": {
      "src": "backgrounds/level-1.jpeg",
      "x": 0,
      "y": -0.3,
      "scale": 0.6108
    }
  },
  {
    "name": "第2关",
    "pathType": "quadratic",
    "curves": [
      {
        "p1": {
          "x": 421,
          "y": 154
        },
        "cp": {
          "x": 229,
          "y": 143
        },
        "p2": {
          "x": 138,
          "y": 157
        }
      },
      {
        "p1": {
          "x": 138,
          "y": 157
        },
        "cp": {
          "x": 45,
          "y": 173
        },
        "p2": {
          "x": 48,
          "y": 346
        }
      },
      {
        "p1": {
          "x": 48,
          "y": 346
        },
        "cp": {
          "x": 51,
          "y": 519
        },
        "p2": {
          "x": 52,
          "y": 606
        }
      },
      {
        "p1": {
          "x": 52,
          "y": 606
        },
        "cp": {
          "x": 53,
          "y": 693
        },
        "p2": {
          "x": 135,
          "y": 721
        }
      },
      {
        "p1": {
          "x": 135,
          "y": 721
        },
        "cp": {
          "x": 215,
          "y": 751
        },
        "p2": {
          "x": 295,
          "y": 721
        }
      },
      {
        "p1": {
          "x": 295,
          "y": 721
        },
        "cp": {
          "x": 375,
          "y": 691
        },
        "p2": {
          "x": 390,
          "y": 571
        }
      },
      {
        "p1": {
          "x": 390,
          "y": 571
        },
        "cp": {
          "x": 405,
          "y": 451
        },
        "p2": {
          "x": 385,
          "y": 351
        }
      }
    ],
    "waypoints": [
      {
        "x": 421,
        "y": 178
      },
      {
        "x": 145,
        "y": 180
      },
      {
        "x": 77,
        "y": 223
      },
      {
        "x": 49,
        "y": 326
      },
      {
        "x": 52,
        "y": 638
      },
      {
        "x": 92,
        "y": 722
      },
      {
        "x": 228,
        "y": 760
      },
      {
        "x": 298,
        "y": 744
      },
      {
        "x": 346,
        "y": 709
      },
      {
        "x": 391,
        "y": 587
      },
      {
        "x": 385,
        "y": 375
      }
    ],
    "shooterPos": {
      "x": 215,
      "y": 496
    },
    "background": {
      "src": "backgrounds/level-2.jpeg",
      "x": -0.92,
      "y": -0.3,
      "scale": 0.6108
    }
  },
  {
    "name": "第3关",
    "pathType": "cubic",
    "curves": [
      {
        "p1": {
          "x": 250,
          "y": -25
        },
        "cp1": {
          "x": 250,
          "y": -25
        },
        "cp2": {
          "x": 328,
          "y": 158
        },
        "p2": {
          "x": 359,
          "y": 260
        },
        "smooth": true
      },
      {
        "p1": {
          "x": 359,
          "y": 260
        },
        "cp1": {
          "x": 383,
          "y": 340
        },
        "cp2": {
          "x": 410,
          "y": 464
        },
        "p2": {
          "x": 410,
          "y": 521
        },
        "smooth": true
      },
      {
        "p1": {
          "x": 410,
          "y": 521
        },
        "cp1": {
          "x": 410,
          "y": 578
        },
        "cp2": {
          "x": 400,
          "y": 597
        },
        "p2": {
          "x": 380,
          "y": 632
        },
        "smooth": true
      },
      {
        "p1": {
          "x": 380,
          "y": 632
        },
        "cp1": {
          "x": 361,
          "y": 664
        },
        "cp2": {
          "x": 337,
          "y": 689
        },
        "p2": {
          "x": 304,
          "y": 707
        },
        "smooth": true
      },
      {
        "p1": {
          "x": 304,
          "y": 707
        },
        "cp1": {
          "x": 280,
          "y": 720
        },
        "cp2": {
          "x": 255,
          "y": 730
        },
        "p2": {
          "x": 228,
          "y": 725
        },
        "smooth": true
      },
      {
        "p1": {
          "x": 228,
          "y": 725
        },
        "cp1": {
          "x": 215,
          "y": 723
        },
        "cp2": {
          "x": 201,
          "y": 716
        },
        "p2": {
          "x": 198,
          "y": 704
        },
        "smooth": true
      },
      {
        "p1": {
          "x": 198,
          "y": 704
        },
        "cp1": {
          "x": 193,
          "y": 685
        },
        "cp2": {
          "x": 210,
          "y": 669
        },
        "p2": {
          "x": 224,
          "y": 655
        },
        "smooth": true
      },
      {
        "p1": {
          "x": 224,
          "y": 655
        },
        "cp1": {
          "x": 247,
          "y": 632
        },
        "cp2": {
          "x": 283,
          "y": 633
        },
        "p2": {
          "x": 305,
          "y": 610
        },
        "smooth": true
      },
      {
        "p1": {
          "x": 305,
          "y": 610
        },
        "cp1": {
          "x": 326,
          "y": 588
        },
        "cp2": {
          "x": 339,
          "y": 561
        },
        "p2": {
          "x": 345,
          "y": 531
        },
        "smooth": true
      },
      {
        "p1": {
          "x": 345,
          "y": 531
        },
        "cp1": {
          "x": 356,
          "y": 476
        },
        "cp2": {
          "x": 346,
          "y": 426
        },
        "p2": {
          "x": 332,
          "y": 372
        },
        "smooth": true
      },
      {
        "p1": {
          "x": 332,
          "y": 372
        },
        "cp1": {
          "x": 319,
          "y": 324
        },
        "cp2": {
          "x": 311,
          "y": 275
        },
        "p2": {
          "x": 273,
          "y": 243
        },
        "smooth": true
      },
      {
        "p1": {
          "x": 273,
          "y": 243
        },
        "cp1": {
          "x": 241,
          "y": 215
        },
        "cp2": {
          "x": 199,
          "y": 202
        },
        "p2": {
          "x": 157,
          "y": 209
        },
        "smooth": true
      },
      {
        "p1": {
          "x": 157,
          "y": 209
        },
        "cp1": {
          "x": 119,
          "y": 216
        },
        "cp2": {
          "x": 90,
          "y": 242
        },
        "p2": {
          "x": 69,
          "y": 274
        },
        "smooth": true
      },
      {
        "p1": {
          "x": 69,
          "y": 274
        },
        "cp1": {
          "x": 43,
          "y": 313
        },
        "cp2": {
          "x": 41,
          "y": 357
        },
        "p2": {
          "x": 36,
          "y": 404
        },
        "smooth": true
      },
      {
        "p1": {
          "x": 36,
          "y": 404
        },
        "cp1": {
          "x": 32,
          "y": 442
        },
        "cp2": {
          "x": 34,
          "y": 475
        },
        "p2": {
          "x": 40,
          "y": 512
        },
        "smooth": true
      },
      {
        "p1": {
          "x": 40,
          "y": 512
        },
        "cp1": {
          "x": 47,
          "y": 557
        },
        "cp2": {
          "x": 57,
          "y": 595
        },
        "p2": {
          "x": 75,
          "y": 637
        },
        "smooth": true
      },
      {
        "p1": {
          "x": 75,
          "y": 637
        },
        "cp1": {
          "x": 83,
          "y": 655
        },
        "cp2": {
          "x": 88,
          "y": 676
        },
        "p2": {
          "x": 105,
          "y": 686
        },
        "smooth": true
      },
      {
        "p1": {
          "x": 105,
          "y": 686
        },
        "cp1": {
          "x": 115,
          "y": 692
        },
        "cp2": {
          "x": 128,
          "y": 693
        },
        "p2": {
          "x": 138,
          "y": 687
        },
        "smooth": true
      },
      {
        "p1": {
          "x": 138,
          "y": 687
        },
        "cp1": {
          "x": 157,
          "y": 676
        },
        "cp2": {
          "x": 169,
          "y": 653
        },
        "p2": {
          "x": 169,
          "y": 631
        },
        "smooth": true
      },
      {
        "p1": {
          "x": 169,
          "y": 631
        },
        "cp1": {
          "x": 169,
          "y": 593
        },
        "cp2": {
          "x": 130,
          "y": 572
        },
        "p2": {
          "x": 115,
          "y": 537
        },
        "smooth": true
      },
      {
        "p1": {
          "x": 115,
          "y": 537
        },
        "cp1": {
          "x": 103,
          "y": 508
        },
        "cp2": {
          "x": 92,
          "y": 483
        },
        "p2": {
          "x": 90,
          "y": 452
        },
        "smooth": true
      },
      {
        "p1": {
          "x": 90,
          "y": 452
        },
        "cp1": {
          "x": 88,
          "y": 421
        },
        "cp2": {
          "x": 93,
          "y": 394
        },
        "p2": {
          "x": 102,
          "y": 364
        },
        "smooth": true
      },
      {
        "p1": {
          "x": 102,
          "y": 364
        },
        "cp1": {
          "x": 109,
          "y": 342
        },
        "cp2": {
          "x": 116,
          "y": 323
        },
        "p2": {
          "x": 131,
          "y": 306
        },
        "smooth": true
      },
      {
        "p1": {
          "x": 131,
          "y": 306
        },
        "cp1": {
          "x": 141,
          "y": 294
        },
        "cp2": {
          "x": 167,
          "y": 280
        },
        "p2": {
          "x": 167,
          "y": 280
        },
        "smooth": true
      }
    ],
    "waypoints": [],
    "shooterPos": {
      "x": 227,
      "y": 479
    },
    "background": {
      "src": "backgrounds/level-3.png",
      "x": 0,
      "y": -0.19,
      "scale": 0.5053
    }
  },
  {
    "name": "第4关",
    "pathType": "cubic",
    "curves": [
      {
        "p1": {
          "x": 84,
          "y": 955
        },
        "cp1": {
          "x": 84,
          "y": 955
        },
        "cp2": {
          "x": 79,
          "y": 643
        },
        "p2": {
          "x": 78,
          "y": 623
        },
        "smooth": true
      },
      {
        "p1": {
          "x": 78,
          "y": 623
        },
        "cp1": {
          "x": 77,
          "y": 603
        },
        "cp2": {
          "x": 59,
          "y": 571
        },
        "p2": {
          "x": 50,
          "y": 543
        },
        "smooth": true
      },
      {
        "p1": {
          "x": 50,
          "y": 543
        },
        "cp1": {
          "x": 39,
          "y": 509
        },
        "cp2": {
          "x": 26,
          "y": 480
        },
        "p2": {
          "x": 23,
          "y": 445
        },
        "smooth": true
      },
      {
        "p1": {
          "x": 23,
          "y": 445
        },
        "cp1": {
          "x": 20,
          "y": 401
        },
        "cp2": {
          "x": 27,
          "y": 363
        },
        "p2": {
          "x": 38,
          "y": 321
        },
        "smooth": true
      },
      {
        "p1": {
          "x": 38,
          "y": 321
        },
        "cp1": {
          "x": 50,
          "y": 278
        },
        "cp2": {
          "x": 62,
          "y": 239
        },
        "p2": {
          "x": 89,
          "y": 204
        },
        "smooth": true
      },
      {
        "p1": {
          "x": 89,
          "y": 204
        },
        "cp1": {
          "x": 110,
          "y": 177
        },
        "cp2": {
          "x": 134,
          "y": 157
        },
        "p2": {
          "x": 166,
          "y": 143
        },
        "smooth": true
      },
      {
        "p1": {
          "x": 166,
          "y": 143
        },
        "cp1": {
          "x": 205,
          "y": 126
        },
        "cp2": {
          "x": 243,
          "y": 125
        },
        "p2": {
          "x": 285,
          "y": 125
        },
        "smooth": true
      },
      {
        "p1": {
          "x": 285,
          "y": 125
        },
        "cp1": {
          "x": 312,
          "y": 125
        },
        "cp2": {
          "x": 338,
          "y": 122
        },
        "p2": {
          "x": 360,
          "y": 137
        },
        "smooth": true
      },
      {
        "p1": {
          "x": 360,
          "y": 137
        },
        "cp1": {
          "x": 371,
          "y": 144
        },
        "cp2": {
          "x": 381,
          "y": 156
        },
        "p2": {
          "x": 380,
          "y": 169
        },
        "smooth": true
      },
      {
        "p1": {
          "x": 380,
          "y": 169
        },
        "cp1": {
          "x": 379,
          "y": 183
        },
        "cp2": {
          "x": 367,
          "y": 195
        },
        "p2": {
          "x": 354,
          "y": 200
        },
        "smooth": true
      },
      {
        "p1": {
          "x": 354,
          "y": 200
        },
        "cp1": {
          "x": 321,
          "y": 213
        },
        "cp2": {
          "x": 288,
          "y": 184
        },
        "p2": {
          "x": 252,
          "y": 188
        },
        "smooth": true
      },
      {
        "p1": {
          "x": 252,
          "y": 188
        },
        "cp1": {
          "x": 214,
          "y": 193
        },
        "cp2": {
          "x": 179,
          "y": 203
        },
        "p2": {
          "x": 148,
          "y": 226
        },
        "smooth": true
      },
      {
        "p1": {
          "x": 148,
          "y": 226
        },
        "cp1": {
          "x": 117,
          "y": 249
        },
        "cp2": {
          "x": 98,
          "y": 280
        },
        "p2": {
          "x": 84,
          "y": 316
        },
        "smooth": true
      },
      {
        "p1": {
          "x": 84,
          "y": 316
        },
        "cp1": {
          "x": 68,
          "y": 358
        },
        "cp2": {
          "x": 65,
          "y": 398
        },
        "p2": {
          "x": 69,
          "y": 443
        },
        "smooth": true
      },
      {
        "p1": {
          "x": 69,
          "y": 443
        },
        "cp1": {
          "x": 72,
          "y": 482
        },
        "cp2": {
          "x": 79,
          "y": 516
        },
        "p2": {
          "x": 100,
          "y": 549
        },
        "smooth": true
      },
      {
        "p1": {
          "x": 100,
          "y": 549
        },
        "cp1": {
          "x": 121,
          "y": 582
        },
        "cp2": {
          "x": 147,
          "y": 608
        },
        "p2": {
          "x": 183,
          "y": 624
        },
        "smooth": true
      },
      {
        "p1": {
          "x": 183,
          "y": 624
        },
        "cp1": {
          "x": 216,
          "y": 639
        },
        "cp2": {
          "x": 251,
          "y": 648
        },
        "p2": {
          "x": 286,
          "y": 637
        },
        "smooth": true
      },
      {
        "p1": {
          "x": 286,
          "y": 637
        },
        "cp1": {
          "x": 321,
          "y": 626
        },
        "cp2": {
          "x": 344,
          "y": 598
        },
        "p2": {
          "x": 364,
          "y": 568
        },
        "smooth": true
      },
      {
        "p1": {
          "x": 364,
          "y": 568
        },
        "cp1": {
          "x": 383,
          "y": 540
        },
        "cp2": {
          "x": 390,
          "y": 511
        },
        "p2": {
          "x": 396,
          "y": 478
        },
        "smooth": true
      },
      {
        "p1": {
          "x": 396,
          "y": 478
        },
        "cp1": {
          "x": 401,
          "y": 449
        },
        "cp2": {
          "x": 401,
          "y": 424
        },
        "p2": {
          "x": 396,
          "y": 395
        },
        "smooth": true
      },
      {
        "p1": {
          "x": 396,
          "y": 395
        },
        "cp1": {
          "x": 389,
          "y": 356
        },
        "cp2": {
          "x": 380,
          "y": 320
        },
        "p2": {
          "x": 354,
          "y": 290
        },
        "smooth": true
      },
      {
        "p1": {
          "x": 354,
          "y": 290
        },
        "cp1": {
          "x": 331,
          "y": 262
        },
        "cp2": {
          "x": 302,
          "y": 241
        },
        "p2": {
          "x": 266,
          "y": 236
        },
        "smooth": true
      },
      {
        "p1": {
          "x": 266,
          "y": 236
        },
        "cp1": {
          "x": 231,
          "y": 231
        },
        "cp2": {
          "x": 197,
          "y": 241
        },
        "p2": {
          "x": 169,
          "y": 263
        },
        "smooth": true
      },
      {
        "p1": {
          "x": 169,
          "y": 263
        },
        "cp1": {
          "x": 139,
          "y": 287
        },
        "cp2": {
          "x": 125,
          "y": 321
        },
        "p2": {
          "x": 116,
          "y": 358
        },
        "smooth": true
      },
      {
        "p1": {
          "x": 116,
          "y": 358
        },
        "cp1": {
          "x": 105,
          "y": 401
        },
        "cp2": {
          "x": 105,
          "y": 443
        },
        "p2": {
          "x": 118,
          "y": 486
        },
        "smooth": true
      },
      {
        "p1": {
          "x": 118,
          "y": 486
        },
        "cp1": {
          "x": 129,
          "y": 523
        },
        "cp2": {
          "x": 148,
          "y": 554
        },
        "p2": {
          "x": 179,
          "y": 577
        },
        "smooth": true
      },
      {
        "p1": {
          "x": 179,
          "y": 577
        },
        "cp1": {
          "x": 201,
          "y": 593
        },
        "cp2": {
          "x": 227,
          "y": 602
        },
        "p2": {
          "x": 254,
          "y": 599
        },
        "smooth": true
      },
      {
        "p1": {
          "x": 254,
          "y": 599
        },
        "cp1": {
          "x": 279,
          "y": 596
        },
        "cp2": {
          "x": 300,
          "y": 581
        },
        "p2": {
          "x": 317,
          "y": 562
        },
        "smooth": true
      },
      {
        "p1": {
          "x": 317,
          "y": 562
        },
        "cp1": {
          "x": 337,
          "y": 540
        },
        "cp2": {
          "x": 345,
          "y": 513
        },
        "p2": {
          "x": 351,
          "y": 484
        },
        "smooth": true
      },
      {
        "p1": {
          "x": 351,
          "y": 484
        },
        "cp1": {
          "x": 357,
          "y": 453
        },
        "cp2": {
          "x": 358,
          "y": 424
        },
        "p2": {
          "x": 350,
          "y": 394
        },
        "smooth": true
      },
      {
        "p1": {
          "x": 350,
          "y": 394
        },
        "cp1": {
          "x": 341,
          "y": 363
        },
        "cp2": {
          "x": 303,
          "y": 314
        },
        "p2": {
          "x": 303,
          "y": 314
        },
        "smooth": true
      }
    ],
    "waypoints": [],
    "shooterPos": {
      "x": 236,
      "y": 524
    },
    "background": {
      "src": "backgrounds/level-4.png",
      "x": 0,
      "y": -0.19,
      "scale": 0.5065
    }
  },
  {
    "name": "第5关",
    "pathType": "quadratic",
    "curves": [
      {
        "p1": {
          "x": 456,
          "y": 173
        },
        "cp": {
          "x": 407,
          "y": 283
        },
        "p2": {
          "x": 407,
          "y": 283
        }
      },
      {
        "p1": {
          "x": 407,
          "y": 283
        },
        "cp": {
          "x": 404,
          "y": 292
        },
        "p2": {
          "x": 390,
          "y": 385
        }
      },
      {
        "p1": {
          "x": 390,
          "y": 385
        },
        "cp": {
          "x": 393,
          "y": 360
        },
        "p2": {
          "x": 389,
          "y": 402
        }
      },
      {
        "p1": {
          "x": 389,
          "y": 402
        },
        "cp": {
          "x": 379,
          "y": 476
        },
        "p2": {
          "x": 372,
          "y": 521
        }
      },
      {
        "p1": {
          "x": 372,
          "y": 521
        },
        "cp": {
          "x": 355,
          "y": 632
        },
        "p2": {
          "x": 353,
          "y": 639
        }
      },
      {
        "p1": {
          "x": 353,
          "y": 639
        },
        "cp": {
          "x": 324,
          "y": 712
        },
        "p2": {
          "x": 286,
          "y": 737
        }
      },
      {
        "p1": {
          "x": 286,
          "y": 737
        },
        "cp": {
          "x": 225,
          "y": 778
        },
        "p2": {
          "x": 172,
          "y": 761
        }
      },
      {
        "p1": {
          "x": 172,
          "y": 761
        },
        "cp": {
          "x": 132,
          "y": 748
        },
        "p2": {
          "x": 91,
          "y": 675
        }
      },
      {
        "p1": {
          "x": 91,
          "y": 675
        },
        "cp": {
          "x": 77,
          "y": 648
        },
        "p2": {
          "x": 59,
          "y": 559
        }
      },
      {
        "p1": {
          "x": 59,
          "y": 559
        },
        "cp": {
          "x": 47,
          "y": 495
        },
        "p2": {
          "x": 46,
          "y": 440
        }
      },
      {
        "p1": {
          "x": 46,
          "y": 440
        },
        "cp": {
          "x": 44,
          "y": 367
        },
        "p2": {
          "x": 54,
          "y": 320
        }
      },
      {
        "p1": {
          "x": 54,
          "y": 320
        },
        "cp": {
          "x": 72,
          "y": 237
        },
        "p2": {
          "x": 95,
          "y": 208
        }
      },
      {
        "p1": {
          "x": 95,
          "y": 208
        },
        "cp": {
          "x": 140,
          "y": 151
        },
        "p2": {
          "x": 194,
          "y": 144
        }
      },
      {
        "p1": {
          "x": 194,
          "y": 144
        },
        "cp": {
          "x": 259,
          "y": 135
        },
        "p2": {
          "x": 303,
          "y": 181
        }
      },
      {
        "p1": {
          "x": 303,
          "y": 181
        },
        "cp": {
          "x": 324,
          "y": 202
        },
        "p2": {
          "x": 340,
          "y": 294
        }
      },
      {
        "p1": {
          "x": 340,
          "y": 294
        },
        "cp": {
          "x": 345,
          "y": 323
        },
        "p2": {
          "x": 344,
          "y": 414
        }
      },
      {
        "p1": {
          "x": 344,
          "y": 414
        },
        "cp": {
          "x": 343,
          "y": 498
        },
        "p2": {
          "x": 337,
          "y": 534
        }
      },
      {
        "p1": {
          "x": 337,
          "y": 534
        },
        "cp": {
          "x": 321,
          "y": 630
        },
        "p2": {
          "x": 305,
          "y": 650
        }
      },
      {
        "p1": {
          "x": 305,
          "y": 650
        },
        "cp": {
          "x": 255,
          "y": 712
        },
        "p2": {
          "x": 203,
          "y": 698
        }
      },
      {
        "p1": {
          "x": 203,
          "y": 698
        },
        "cp": {
          "x": 175,
          "y": 691
        },
        "p2": {
          "x": 131,
          "y": 605
        }
      },
      {
        "p1": {
          "x": 131,
          "y": 605
        },
        "cp": {
          "x": 109,
          "y": 562
        },
        "p2": {
          "x": 96,
          "y": 490
        }
      },
      {
        "p1": {
          "x": 96,
          "y": 490
        },
        "cp": {
          "x": 96,
          "y": 490
        },
        "p2": {
          "x": 89,
          "y": 370
        }
      }
    ],
    "waypoints": [
      {
        "x": 456,
        "y": 173
      },
      {
        "x": 405,
        "y": 294
      },
      {
        "x": 351,
        "y": 643
      },
      {
        "x": 310,
        "y": 716
      },
      {
        "x": 251,
        "y": 756
      },
      {
        "x": 158,
        "y": 755
      },
      {
        "x": 90,
        "y": 672
      },
      {
        "x": 53,
        "y": 521
      },
      {
        "x": 48,
        "y": 366
      },
      {
        "x": 78,
        "y": 238
      },
      {
        "x": 139,
        "y": 165
      },
      {
        "x": 231,
        "y": 144
      },
      {
        "x": 304,
        "y": 182
      },
      {
        "x": 342,
        "y": 307
      },
      {
        "x": 341,
        "y": 499
      },
      {
        "x": 311,
        "y": 639
      },
      {
        "x": 261,
        "y": 689
      },
      {
        "x": 193,
        "y": 693
      },
      {
        "x": 137,
        "y": 616
      },
      {
        "x": 98,
        "y": 503
      },
      {
        "x": 89,
        "y": 371
      }
    ],
    "shooterPos": {
      "x": 219,
      "y": 419
    }
  },
  {
    "name": "第6关",
    "pathType": "cubic",
    "curves": [
      {
        "p1": {
          "x": -19,
          "y": 717
        },
        "cp1": {
          "x": -19,
          "y": 717
        },
        "cp2": {
          "x": 47,
          "y": 718
        },
        "p2": {
          "x": 83,
          "y": 718
        },
        "smooth": true
      },
      {
        "p1": {
          "x": 83,
          "y": 718
        },
        "cp1": {
          "x": 123,
          "y": 718
        },
        "cp2": {
          "x": 158,
          "y": 720
        },
        "p2": {
          "x": 198,
          "y": 717
        },
        "smooth": true
      },
      {
        "p1": {
          "x": 198,
          "y": 717
        },
        "cp1": {
          "x": 228,
          "y": 715
        },
        "cp2": {
          "x": 254,
          "y": 715
        },
        "p2": {
          "x": 283,
          "y": 707
        },
        "smooth": true
      },
      {
        "p1": {
          "x": 283,
          "y": 707
        },
        "cp1": {
          "x": 306,
          "y": 700
        },
        "cp2": {
          "x": 325,
          "y": 692
        },
        "p2": {
          "x": 344,
          "y": 678
        },
        "smooth": true
      },
      {
        "p1": {
          "x": 344,
          "y": 678
        },
        "cp1": {
          "x": 360,
          "y": 666
        },
        "cp2": {
          "x": 374,
          "y": 654
        },
        "p2": {
          "x": 383,
          "y": 637
        },
        "smooth": true
      },
      {
        "p1": {
          "x": 383,
          "y": 637
        },
        "cp1": {
          "x": 393,
          "y": 617
        },
        "cp2": {
          "x": 395,
          "y": 597
        },
        "p2": {
          "x": 397,
          "y": 575
        },
        "smooth": true
      },
      {
        "p1": {
          "x": 397,
          "y": 575
        },
        "cp1": {
          "x": 398,
          "y": 554
        },
        "cp2": {
          "x": 397,
          "y": 536
        },
        "p2": {
          "x": 392,
          "y": 516
        },
        "smooth": true
      },
      {
        "p1": {
          "x": 392,
          "y": 516
        },
        "cp1": {
          "x": 382,
          "y": 471
        },
        "cp2": {
          "x": 368,
          "y": 433
        },
        "p2": {
          "x": 346,
          "y": 393
        },
        "smooth": true
      },
      {
        "p1": {
          "x": 346,
          "y": 393
        },
        "cp1": {
          "x": 327,
          "y": 358
        },
        "cp2": {
          "x": 304,
          "y": 331
        },
        "p2": {
          "x": 277,
          "y": 301
        },
        "smooth": true
      },
      {
        "p1": {
          "x": 277,
          "y": 301
        },
        "cp1": {
          "x": 259,
          "y": 281
        },
        "cp2": {
          "x": 243,
          "y": 263
        },
        "p2": {
          "x": 220,
          "y": 249
        },
        "smooth": true
      },
      {
        "p1": {
          "x": 220,
          "y": 249
        },
        "cp1": {
          "x": 200,
          "y": 237
        },
        "cp2": {
          "x": 180,
          "y": 228
        },
        "p2": {
          "x": 157,
          "y": 226
        },
        "smooth": true
      },
      {
        "p1": {
          "x": 157,
          "y": 226
        },
        "cp1": {
          "x": 140,
          "y": 225
        },
        "cp2": {
          "x": 123,
          "y": 226
        },
        "p2": {
          "x": 108,
          "y": 235
        },
        "smooth": true
      },
      {
        "p1": {
          "x": 108,
          "y": 235
        },
        "cp1": {
          "x": 88,
          "y": 247
        },
        "cp2": {
          "x": 76,
          "y": 265
        },
        "p2": {
          "x": 66,
          "y": 286
        },
        "smooth": true
      },
      {
        "p1": {
          "x": 66,
          "y": 286
        },
        "cp1": {
          "x": 45,
          "y": 330
        },
        "cp2": {
          "x": 43,
          "y": 374
        },
        "p2": {
          "x": 40,
          "y": 422
        },
        "smooth": true
      },
      {
        "p1": {
          "x": 40,
          "y": 422
        },
        "cp1": {
          "x": 37,
          "y": 464
        },
        "cp2": {
          "x": 36,
          "y": 502
        },
        "p2": {
          "x": 46,
          "y": 543
        },
        "smooth": true
      },
      {
        "p1": {
          "x": 46,
          "y": 543
        },
        "cp1": {
          "x": 54,
          "y": 575
        },
        "cp2": {
          "x": 63,
          "y": 605
        },
        "p2": {
          "x": 85,
          "y": 630
        },
        "smooth": true
      },
      {
        "p1": {
          "x": 85,
          "y": 630
        },
        "cp1": {
          "x": 99,
          "y": 646
        },
        "cp2": {
          "x": 116,
          "y": 656
        },
        "p2": {
          "x": 136,
          "y": 661
        },
        "smooth": true
      },
      {
        "p1": {
          "x": 136,
          "y": 661
        },
        "cp1": {
          "x": 181,
          "y": 673
        },
        "cp2": {
          "x": 240,
          "y": 668
        },
        "p2": {
          "x": 269,
          "y": 658
        },
        "smooth": true
      },
      {
        "p1": {
          "x": 269,
          "y": 658
        },
        "cp1": {
          "x": 298,
          "y": 648
        },
        "cp2": {
          "x": 331,
          "y": 624
        },
        "p2": {
          "x": 331,
          "y": 624
        },
        "smooth": false
      },
      {
        "p1": {
          "x": 331,
          "y": 624
        },
        "cp1": {
          "x": 331,
          "y": 624
        },
        "cp2": {
          "x": 246,
          "y": 598
        },
        "p2": {
          "x": 203,
          "y": 579
        },
        "smooth": true
      },
      {
        "p1": {
          "x": 203,
          "y": 579
        },
        "cp1": {
          "x": 174,
          "y": 566
        },
        "cp2": {
          "x": 144,
          "y": 559
        },
        "p2": {
          "x": 122,
          "y": 536
        },
        "smooth": true
      },
      {
        "p1": {
          "x": 122,
          "y": 536
        },
        "cp1": {
          "x": 103,
          "y": 516
        },
        "cp2": {
          "x": 92,
          "y": 492
        },
        "p2": {
          "x": 87,
          "y": 464
        },
        "smooth": true
      },
      {
        "p1": {
          "x": 87,
          "y": 464
        },
        "cp1": {
          "x": 81,
          "y": 431
        },
        "cp2": {
          "x": 86,
          "y": 400
        },
        "p2": {
          "x": 98,
          "y": 369
        },
        "smooth": true
      },
      {
        "p1": {
          "x": 98,
          "y": 369
        },
        "cp1": {
          "x": 109,
          "y": 342
        },
        "cp2": {
          "x": 121,
          "y": 316
        },
        "p2": {
          "x": 147,
          "y": 303
        },
        "smooth": true
      },
      {
        "p1": {
          "x": 147,
          "y": 303
        },
        "cp1": {
          "x": 163,
          "y": 295
        },
        "cp2": {
          "x": 181,
          "y": 297
        },
        "p2": {
          "x": 197,
          "y": 304
        },
        "smooth": true
      },
      {
        "p1": {
          "x": 197,
          "y": 304
        },
        "cp1": {
          "x": 227,
          "y": 316
        },
        "cp2": {
          "x": 242,
          "y": 343
        },
        "p2": {
          "x": 263,
          "y": 367
        },
        "smooth": true
      },
      {
        "p1": {
          "x": 263,
          "y": 367
        },
        "cp1": {
          "x": 283,
          "y": 390
        },
        "cp2": {
          "x": 298,
          "y": 411
        },
        "p2": {
          "x": 314,
          "y": 437
        },
        "smooth": true
      },
      {
        "p1": {
          "x": 314,
          "y": 437
        },
        "cp1": {
          "x": 327,
          "y": 459
        },
        "cp2": {
          "x": 340,
          "y": 477
        },
        "p2": {
          "x": 347,
          "y": 502
        },
        "smooth": true
      },
      {
        "p1": {
          "x": 347,
          "y": 502
        },
        "cp1": {
          "x": 350,
          "y": 512
        },
        "cp2": {
          "x": 351,
          "y": 525
        },
        "p2": {
          "x": 343,
          "y": 531
        },
        "smooth": true
      },
      {
        "p1": {
          "x": 343,
          "y": 531
        },
        "cp1": {
          "x": 325,
          "y": 544
        },
        "cp2": {
          "x": 280,
          "y": 519
        },
        "p2": {
          "x": 280,
          "y": 519
        },
        "smooth": true
      }
    ],
    "waypoints": [],
    "shooterPos": {
      "x": 195,
      "y": 435
    },
    "background": {
      "src": "backgrounds/level-6.png",
      "x": -0.3,
      "y": 0.02,
      "scale": 0.6108
    }
  },
  {
    "name": "第7关",
    "pathType": "quadratic",
    "curves": [
      {
        "p1": {
          "x": 270,
          "y": 90
        },
        "cp": {
          "x": 295,
          "y": 143
        },
        "p2": {
          "x": 320,
          "y": 196
        }
      },
      {
        "p1": {
          "x": 320,
          "y": 196
        },
        "cp": {
          "x": 352,
          "y": 265
        },
        "p2": {
          "x": 364,
          "y": 310
        }
      },
      {
        "p1": {
          "x": 364,
          "y": 310
        },
        "cp": {
          "x": 401,
          "y": 453
        },
        "p2": {
          "x": 384,
          "y": 574
        }
      },
      {
        "p1": {
          "x": 384,
          "y": 574
        },
        "cp": {
          "x": 373,
          "y": 642
        },
        "p2": {
          "x": 326,
          "y": 680
        }
      },
      {
        "p1": {
          "x": 326,
          "y": 680
        },
        "cp": {
          "x": 314,
          "y": 688
        },
        "p2": {
          "x": 303,
          "y": 698
        }
      },
      {
        "p1": {
          "x": 303,
          "y": 698
        },
        "cp": {
          "x": 300,
          "y": 700
        },
        "p2": {
          "x": 294,
          "y": 705
        }
      },
      {
        "p1": {
          "x": 294,
          "y": 705
        },
        "cp": {
          "x": 287,
          "y": 711
        },
        "p2": {
          "x": 280,
          "y": 716
        }
      },
      {
        "p1": {
          "x": 280,
          "y": 716
        },
        "cp": {
          "x": 240,
          "y": 743
        },
        "p2": {
          "x": 213,
          "y": 715
        }
      },
      {
        "p1": {
          "x": 213,
          "y": 715
        },
        "cp": {
          "x": 172,
          "y": 671
        },
        "p2": {
          "x": 199,
          "y": 656
        }
      },
      {
        "p1": {
          "x": 199,
          "y": 656
        },
        "cp": {
          "x": 202,
          "y": 653
        },
        "p2": {
          "x": 210,
          "y": 653
        }
      },
      {
        "p1": {
          "x": 210,
          "y": 653
        },
        "cp": {
          "x": 214,
          "y": 655
        },
        "p2": {
          "x": 220,
          "y": 650
        }
      },
      {
        "p1": {
          "x": 220,
          "y": 650
        },
        "cp": {
          "x": 226,
          "y": 646
        },
        "p2": {
          "x": 247,
          "y": 638
        }
      },
      {
        "p1": {
          "x": 247,
          "y": 638
        },
        "cp": {
          "x": 308,
          "y": 612
        },
        "p2": {
          "x": 335,
          "y": 550
        }
      },
      {
        "p1": {
          "x": 335,
          "y": 550
        },
        "cp": {
          "x": 347,
          "y": 527
        },
        "p2": {
          "x": 345,
          "y": 485
        }
      },
      {
        "p1": {
          "x": 345,
          "y": 485
        },
        "cp": {
          "x": 344,
          "y": 476
        },
        "p2": {
          "x": 340,
          "y": 457
        }
      },
      {
        "p1": {
          "x": 340,
          "y": 457
        },
        "cp": {
          "x": 337,
          "y": 442
        },
        "p2": {
          "x": 333,
          "y": 428
        }
      },
      {
        "p1": {
          "x": 333,
          "y": 428
        },
        "cp": {
          "x": 317,
          "y": 360
        },
        "p2": {
          "x": 306,
          "y": 334
        }
      },
      {
        "p1": {
          "x": 306,
          "y": 334
        },
        "cp": {
          "x": 299,
          "y": 318
        },
        "p2": {
          "x": 291,
          "y": 302
        }
      },
      {
        "p1": {
          "x": 291,
          "y": 302
        },
        "cp": {
          "x": 278,
          "y": 275
        },
        "p2": {
          "x": 272,
          "y": 266
        }
      },
      {
        "p1": {
          "x": 272,
          "y": 266
        },
        "cp": {
          "x": 247,
          "y": 225
        },
        "p2": {
          "x": 231,
          "y": 224
        }
      },
      {
        "p1": {
          "x": 231,
          "y": 224
        },
        "cp": {
          "x": 227,
          "y": 223
        },
        "p2": {
          "x": 219,
          "y": 224
        }
      },
      {
        "p1": {
          "x": 219,
          "y": 224
        },
        "cp": {
          "x": 211,
          "y": 224
        },
        "p2": {
          "x": 202,
          "y": 223
        }
      },
      {
        "p1": {
          "x": 202,
          "y": 223
        },
        "cp": {
          "x": 185,
          "y": 222
        },
        "p2": {
          "x": 167,
          "y": 223
        }
      },
      {
        "p1": {
          "x": 167,
          "y": 223
        },
        "cp": {
          "x": 121,
          "y": 225
        },
        "p2": {
          "x": 89,
          "y": 244
        }
      },
      {
        "p1": {
          "x": 89,
          "y": 244
        },
        "cp": {
          "x": 70,
          "y": 256
        },
        "p2": {
          "x": 54,
          "y": 304
        }
      },
      {
        "p1": {
          "x": 54,
          "y": 304
        },
        "cp": {
          "x": 43,
          "y": 336
        },
        "p2": {
          "x": 42,
          "y": 360
        }
      },
      {
        "p1": {
          "x": 42,
          "y": 360
        },
        "cp": {
          "x": 37,
          "y": 431
        },
        "p2": {
          "x": 39,
          "y": 471
        }
      },
      {
        "p1": {
          "x": 39,
          "y": 471
        },
        "cp": {
          "x": 40,
          "y": 510
        },
        "p2": {
          "x": 43,
          "y": 527
        }
      },
      {
        "p1": {
          "x": 43,
          "y": 527
        },
        "cp": {
          "x": 48,
          "y": 566
        },
        "p2": {
          "x": 52,
          "y": 582
        }
      },
      {
        "p1": {
          "x": 52,
          "y": 582
        },
        "cp": {
          "x": 72,
          "y": 711
        },
        "p2": {
          "x": 130,
          "y": 696
        }
      },
      {
        "p1": {
          "x": 130,
          "y": 696
        },
        "cp": {
          "x": 187,
          "y": 680
        },
        "p2": {
          "x": 164,
          "y": 636
        }
      },
      {
        "p1": {
          "x": 164,
          "y": 636
        },
        "cp": {
          "x": 162,
          "y": 633
        },
        "p2": {
          "x": 159,
          "y": 626
        }
      },
      {
        "p1": {
          "x": 159,
          "y": 626
        },
        "cp": {
          "x": 158,
          "y": 622
        },
        "p2": {
          "x": 153,
          "y": 616
        }
      },
      {
        "p1": {
          "x": 153,
          "y": 616
        },
        "cp": {
          "x": 148,
          "y": 608
        },
        "p2": {
          "x": 143,
          "y": 597
        }
      },
      {
        "p1": {
          "x": 143,
          "y": 597
        },
        "cp": {
          "x": 136,
          "y": 581
        },
        "p2": {
          "x": 124,
          "y": 562
        }
      },
      {
        "p1": {
          "x": 124,
          "y": 562
        },
        "cp": {
          "x": 100,
          "y": 522
        },
        "p2": {
          "x": 87,
          "y": 476
        }
      },
      {
        "p1": {
          "x": 87,
          "y": 476
        },
        "cp": {
          "x": 78,
          "y": 446
        },
        "p2": {
          "x": 94,
          "y": 388
        }
      },
      {
        "p1": {
          "x": 94,
          "y": 388
        },
        "cp": {
          "x": 97,
          "y": 380
        },
        "p2": {
          "x": 101,
          "y": 365
        }
      },
      {
        "p1": {
          "x": 101,
          "y": 365
        },
        "cp": {
          "x": 106,
          "y": 343
        },
        "p2": {
          "x": 110,
          "y": 336
        }
      },
      {
        "p1": {
          "x": 110,
          "y": 336
        },
        "cp": {
          "x": 120,
          "y": 312
        },
        "p2": {
          "x": 140,
          "y": 307
        }
      },
      {
        "p1": {
          "x": 140,
          "y": 307
        },
        "cp": {
          "x": 149,
          "y": 306
        },
        "p2": {
          "x": 174,
          "y": 303
        }
      },
      {
        "p1": {
          "x": 174,
          "y": 303
        },
        "cp": {
          "x": 191,
          "y": 301
        },
        "p2": {
          "x": 208,
          "y": 298
        }
      }
    ],
    "waypoints": [
      {
        "x": 270,
        "y": 90
      },
      {
        "x": 352,
        "y": 265
      },
      {
        "x": 389,
        "y": 406
      },
      {
        "x": 396,
        "y": 492
      },
      {
        "x": 381,
        "y": 598
      },
      {
        "x": 345,
        "y": 666
      },
      {
        "x": 280,
        "y": 716
      },
      {
        "x": 225,
        "y": 727
      },
      {
        "x": 190,
        "y": 691
      },
      {
        "x": 199,
        "y": 656
      },
      {
        "x": 220,
        "y": 650
      },
      {
        "x": 268,
        "y": 628
      },
      {
        "x": 316,
        "y": 587
      },
      {
        "x": 341,
        "y": 540
      },
      {
        "x": 345,
        "y": 479
      },
      {
        "x": 318,
        "y": 361
      },
      {
        "x": 276,
        "y": 270
      },
      {
        "x": 231,
        "y": 224
      },
      {
        "x": 121,
        "y": 222
      },
      {
        "x": 70,
        "y": 256
      },
      {
        "x": 43,
        "y": 336
      },
      {
        "x": 37,
        "y": 431
      },
      {
        "x": 41,
        "y": 510
      },
      {
        "x": 50,
        "y": 576
      },
      {
        "x": 74,
        "y": 642
      },
      {
        "x": 102,
        "y": 684
      },
      {
        "x": 130,
        "y": 696
      },
      {
        "x": 150,
        "y": 673
      },
      {
        "x": 164,
        "y": 636
      },
      {
        "x": 135,
        "y": 582
      },
      {
        "x": 101,
        "y": 522
      },
      {
        "x": 82,
        "y": 459
      },
      {
        "x": 91,
        "y": 399
      },
      {
        "x": 110,
        "y": 336
      },
      {
        "x": 140,
        "y": 307
      },
      {
        "x": 208,
        "y": 298
      }
    ],
    "shooterPos": {
      "x": 217,
      "y": 484
    }
  },
  {
    "name": "第8关",
    "pathType": "quadratic",
    "curves": [
      {
        "p1": {
          "x": 348,
          "y": 198
        },
        "cp": {
          "x": 353,
          "y": 218
        },
        "p2": {
          "x": 357,
          "y": 239
        }
      },
      {
        "p1": {
          "x": 357,
          "y": 239
        },
        "cp": {
          "x": 359,
          "y": 250
        },
        "p2": {
          "x": 362,
          "y": 262
        }
      },
      {
        "p1": {
          "x": 362,
          "y": 262
        },
        "cp": {
          "x": 366,
          "y": 277
        },
        "p2": {
          "x": 367,
          "y": 285
        }
      },
      {
        "p1": {
          "x": 367,
          "y": 285
        },
        "cp": {
          "x": 378,
          "y": 346
        },
        "p2": {
          "x": 377,
          "y": 377
        }
      },
      {
        "p1": {
          "x": 377,
          "y": 377
        },
        "cp": {
          "x": 374,
          "y": 424
        },
        "p2": {
          "x": 365,
          "y": 476
        }
      },
      {
        "p1": {
          "x": 365,
          "y": 476
        },
        "cp": {
          "x": 352,
          "y": 550
        },
        "p2": {
          "x": 308,
          "y": 574
        }
      },
      {
        "p1": {
          "x": 308,
          "y": 574
        },
        "cp": {
          "x": 263,
          "y": 599
        },
        "p2": {
          "x": 229,
          "y": 593
        }
      },
      {
        "p1": {
          "x": 229,
          "y": 593
        },
        "cp": {
          "x": 132,
          "y": 577
        },
        "p2": {
          "x": 138,
          "y": 472
        }
      },
      {
        "p1": {
          "x": 138,
          "y": 472
        },
        "cp": {
          "x": 141,
          "y": 418
        },
        "p2": {
          "x": 157,
          "y": 340
        }
      }
    ],
    "waypoints": [
      {
        "x": 348,
        "y": 198
      },
      {
        "x": 369,
        "y": 297
      },
      {
        "x": 378,
        "y": 365
      },
      {
        "x": 370,
        "y": 448
      },
      {
        "x": 359,
        "y": 514
      },
      {
        "x": 328,
        "y": 563
      },
      {
        "x": 263,
        "y": 598
      },
      {
        "x": 190,
        "y": 587
      },
      {
        "x": 151,
        "y": 550
      },
      {
        "x": 137,
        "y": 488
      },
      {
        "x": 140,
        "y": 440
      },
      {
        "x": 147,
        "y": 390
      },
      {
        "x": 157,
        "y": 340
      }
    ],
    "shooterPos": {
      "x": 215,
      "y": 764
    }
  }
]